[{"puuid": "UxsPSNijXYNJ0Kca3r_NYFlP1aUNV6bTyajsKSDYe7Z96PkYbMhQr_0r6rFnMMTYJUn-jWNzq4YqxQ", "profileIcon": 4077, "championName": "Shen", "championId": 98, "lane": "NONE", "kills": 0, "deaths": 3, "assists": 4, "item0": 1054, "item1": 6660, "item2": 3047, "item3": 3105, "item4": 0, "item5": 0, "item6": 3340, "goldEarned": 4178, "detectorWardsPlaced": 0, "win": false}, {"puuid": "ODPFn_7pKgVKHPARXLtac8i4D2LEba3gIAePx7OQS9s1JMco6Skkw0OUTFxo97U0cyI6Qh1fLWQROw", "profileIcon": 3788, "championName": "Shaco", "championId": 35, "lane": "NONE", "kills": 5, "deaths": 2, "assists": 0, "item0": 0, "item1": 2031, "item2": 6691, "item3": 1042, "item4": 1001, "item5": 0, "item6": 3364, "goldEarned": 5373, "detectorWardsPlaced": 1, "win": false}, {"puuid": "bUccAfrftH77mx9z1srA2YwwiYqV2Fx8f2Gb1KayRDXNAN2RHmqD9NDVmBlGG73hdEMNiI6V0TrSyw", "profileIcon": 1393, "championName": "Lux", "championId": 99, "lane": "NONE", "kills": 0, "deaths": 2, "assists": 1, "item0": 1056, "item1": 3802, "item2": 1001, "item3": 1026, "item4": 0, "item5": 0, "item6": 3340, "goldEarned": 4058, "detectorWardsPlaced": 1, "win": false}, {"puuid": "s7P0jyYqAEOODzF_u5RZO8BP-XjnbR1xlPVmLgeDAqJFvpq1BvTmvJF4fTU4Rh_Nx4lqjLtciiN-7g", "profileIcon": 5030, "championName": "Zeri", "championId": 221, "lane": "NONE", "kills": 2, "deaths": 5, "assists": 2, "item0": 3078, "item1": 3006, "item2": 1036, "item3": 0, "item4": 1055, "item5": 0, "item6": 3340, "goldEarned": 5615, "detectorWardsPlaced": 0, "win": false}, {"puuid": "TnlnLbdH0t4Fqu0SBdZpdi4GO_n3mIC0P2rRFVxaPsVzgMET1TZMD2mS-M0b7zPU_lx6lxzyGKLZCg", "profileIcon": 4864, "championName": "Senna", "championId": 235, "lane": "NONE", "kills": 0, "deaths": 9, "assists": 3, "item0": 3863, "item1": 3133, "item2": 3035, "item3": 3006, "item4": 0, "item5": 0, "item6": 3364, "goldEarned": 4125, "detectorWardsPlaced": 0, "win": false}, {"puuid": "-iCVqLGS-Pi-LiNHKDnhJe5rdBdtSx0rd-da0Wk2RgCBKckoiXA9YR4tT_WQLFVB-afcQFZQWr4Ppw", "profileIcon": 654, "championName": "Urgot", "championId": 6, "lane": "NONE", "kills": 2, "deaths": 1, "assists": 0, "item0": 3047, "item1": 3181, "item2": 3077, "item3": 2003, "item4": 0, "item5": 0, "item6": 3340, "goldEarned": 5866, "detectorWardsPlaced": 1, "win": true}, {"puuid": "yZCdDAGRh935-M-wi8nceWlon0ZloQBUllz9ssoI2vOLhfYsdB_5cfhjQjquudbK-vZHLVnKeVAxxg", "profileIcon": 3398, "championName": "Nocturne", "championId": 56, "lane": "NONE", "kills": 4, "deaths": 0, "assists": 1, "item0": 3047, "item1": 1036, "item2": 6693, "item3": 0, "item4": 0, "item5": 0, "item6": 3340, "goldEarned": 6077, "detectorWardsPlaced": 0, "win": true}, {"puuid": "Wn-FrIp544B6ca5pi8JwfqCHl158ISwak_qArFNVoR03eHJDcQPAzcGUgywp4XqvJphDNXS8cc44qg", "profileIcon": 950, "championName": "Ziggs", "championId": 115, "lane": "NONE", "kills": 1, "deaths": 1, "assists": 2, "item0": 1056, "item1": 6655, "item2": 3020, "item3": 1052, "item4": 0, "item5": 0, "item6": 3340, "goldEarned": 6382, "detectorWardsPlaced": 0, "win": true}, {"puuid": "4vULtHgXBliudnQWpBr526rjelQLrpJFd4wGb6D4D96HFU0UY2GYGj8_vF4HyG1kJbO0NLy5s6P8bQ", "profileIcon": 23, "championName": "Lucian", "championId": 236, "lane": "NONE", "kills": 8, "deaths": 2, "assists": 8, "item0": 3508, "item1": 1037, "item2": 3006, "item3": 0, "item4": 6670, "item5": 0, "item6": 3340, "goldEarned": 8216, "detectorWardsPlaced": 0, "win": true}, {"puuid": "Um8mgRn6GciHjWUXZisMDt-TXPyFVW44ApbpedSJJm5ICwBOgnf8P_58pmm_82jaJ9e14ZhnjCAC1w", "profileIcon": 23, "championName": "Bard", "championId": 432, "lane": "NONE", "kills": 6, "deaths": 3, "assists": 8, "item0": 6655, "item1": 3145, "item2": 3158, "item3": 3853, "item4": 0, "item5": 0, "item6": 3364, "goldEarned": 6886, "detectorWardsPlaced": 0, "win": true}, {"gameDuration": 930, "gameMode": "CLASSIC", "gameType": "MATCHED_GAME"}]